Workbook
Name SCN: 가정!$E$1
Name WACC: 가정!$C$15
Name TermG: 가정!$C$16
Name TaxRate: 가정!$C$7

Sheet Cover
B2: 3-STATEMENT FINANCIAL MODEL
B3: 가상 제조업 · Initiation Model (교육용)
B5: 시나리오 선택 → | C5: 1 | D5: 1=Base · 2=Bull · 3=Bear
B7: 목 차 | E7: 핵심 결과 (활성 시나리오)
B8: ① 가정 & 시나리오 | E8: 시나리오 | G8: =Output!C4
B9: ② 손익계산서 (IS) | E9: 목표주가 | G9: =Output!C7
B10: ③ 재무상태표 (BS) | E10: 현재주가 | G10: =Output!C8
B11: ④ 현금흐름표 (CF) | E11: 상승여력 | G11: =Output!C9
B12: ⑤ 재무비율 대시보드 | E12: 투자의견 | G12: =Output!C10
B13: ⑥ DCF 밸류에이션
B14: ⑦ 투자 요약

Sheet 가정
B1: 가정 & 시나리오 (Assumptions) | D1: 시나리오 | E1: 1 | F1: 1=Base 2=Bull 3=Bear
B2: 파랑=입력 · 활성값(C열)=CHOOSE로 시나리오 전환 · 단위: 억원
B3: 항목 | C3: 활성값 | D3: ①Base | E3: ②Bull | F3: ③Bear | G3: 비고
B4: 매출성장률 (추정) | C4: =CHOOSE($E$1,D4,E4,F4) | D4: 0.07 | E4: 0.1 | F4: 0.04 | G4: YoY
B5: 매출원가율 | C5: =CHOOSE($E$1,D5,E5,F5) | D5: 0.62 | E5: 0.6 | F5: 0.65
B6: 판매관리비율 | C6: =CHOOSE($E$1,D6,E6,F6) | D6: 0.2 | E6: 0.19 | F6: 0.22
B7: 법인세율 | C7: =CHOOSE($E$1,D7,E7,F7) | D7: 0.22 | E7: 0.22 | F7: 0.22
B8: Capex / 매출 | C8: =CHOOSE($E$1,D8,E8,F8) | D8: 0.05 | E8: 0.05 | F8: 0.06
B9: 감가상각률 | C9: =CHOOSE($E$1,D9,E9,F9) | D9: 0.1 | E9: 0.1 | F9: 0.1 | G9: 기초 유형자산 대비
B10: 매출채권 DSO(일) | C10: =CHOOSE($E$1,D10,E10,F10) | D10: 45 | E10: 40 | F10: 55
B11: 재고자산 DIO(일) | C11: =CHOOSE($E$1,D11,E11,F11) | D11: 60 | E11: 55 | F11: 70
B12: 매입채무 DPO(일) | C12: =CHOOSE($E$1,D12,E12,F12) | D12: 40 | E12: 45 | F12: 35
B13: 배당성향 | C13: =CHOOSE($E$1,D13,E13,F13) | D13: 0.2 | E13: 0.2 | F13: 0.15
B14: 차입금 이자율 | C14: =CHOOSE($E$1,D14,E14,F14) | D14: 0.045 | E14: 0.04 | F14: 0.055
B15: WACC | C15: =CHOOSE($E$1,D15,E15,F15) | D15: 0.09 | E15: 0.085 | F15: 0.1
B16: 영구성장률 g | C16: =CHOOSE($E$1,D16,E16,F16) | D16: 0.02 | E16: 0.025 | F16: 0.015 | G16: < WACC
B17: 주식수(백만주) | C17: =CHOOSE($E$1,D17,E17,F17) | D17: 50 | E17: 50 | F17: 50

Sheet IS
B1: 손익계산서 (Income Statement)
B2: 단위: 억원
B3: 항목 | C3: 2022A | D3: 2023A | E3: 2024A | F3: 2025E | G3: 2026E | H3: 2027E
B4: 매출액 | C4: 1000 | D4: 1120 | E4: 1230
B5: (-) 매출원가 | C5: 620 | D5: 694 | E5: 763
B6: 매출총이익 | C6: =C4-C5 | D6: =D4-D5 | E6: =E4-E5
B7: (-) 판매관리비 | C7: 200 | D7: 224 | E7: 246
B8: 영업이익 (EBIT) | C8: =C6-C7 | D8: =D6-D7 | E8: =E6-E7
B9: (-) 이자비용 | C9: 18 | D9: 19 | E9: 20
B10: 세전이익 | C10: =C8-C9 | D10: =D8-D9 | E10: =E8-E9
B11: (-) 법인세 | C11: 36 | D11: 40 | E11: 44
B12: 당기순이익 | C12: =C10-C11 | D12: =D10-D11 | E12: =E10-E11
B14: 매출성장률 | D14: =IFERROR(D4/C4-1,"-") | E14: =IFERROR(E4/D4-1,"-")
B15: 영업이익률 | C15: =IFERROR(C8/C4,"-") | D15: =IFERROR(D8/D4,"-") | E15: =IFERROR(E8/E4,"-")
B17: ↑ 추정연도(2025~2027)가 비어 있습니다 — R4를 보며 직접 채우세요.

Sheet BS
B1: 재무상태표 (Balance Sheet)
B2: 단위: 억원
B3: 항목 | C3: 2022A | D3: 2023A | E3: 2024A | F3: 2025E | G3: 2026E | H3: 2027E
B5: [ 자산 ]
B6: 현금및현금성자산 | C6: 344 | D6: 419 | E6: 508
B7: 매출채권 | C7: 123 | D7: 138 | E7: 152
B8: 재고자산 | C8: 102 | D8: 114 | E8: 125
B9: 유형자산(순) | C9: 500 | D9: 540 | E9: 580
B10: 자산총계 | C10: =SUM(C6:C9) | D10: =SUM(D6:D9) | E10: =SUM(E6:E9) | F10: =SUM(F6:F9) | G10: =SUM(G6:G9) | H10: =SUM(H6:H9)
B12: [ 부채 ]
B13: 매입채무 | C13: 68 | D13: 76 | E13: 84
B14: 차입금 | C14: 400 | D14: 420 | E14: 440
B15: 부채총계 | C15: =SUM(C13:C14) | D15: =SUM(D13:D14) | E15: =SUM(E13:E14) | F15: =SUM(F13:F14) | G15: =SUM(G13:G14) | H15: =SUM(H13:H14)
B17: [ 자본 ]
B18: 자본금 | C18: 300 | D18: 300 | E18: 300
B19: 이익잉여금 | C19: 301 | D19: 415 | E19: 541
B20: 자본총계 | C20: =SUM(C18:C19) | D20: =SUM(D18:D19) | E20: =SUM(E18:E19) | F20: =SUM(F18:F19) | G20: =SUM(G18:G19) | H20: =SUM(H18:H19)
B21: 부채와자본총계 | C21: =C15+C20 | D21: =D15+D20 | E21: =E15+E20 | F21: =F15+F20 | G21: =G15+G20 | H21: =H15+H20
B23: 검증 (자산-부채-자본) | C23: =C10-C21 | D23: =D10-D21 | E23: =E10-E21 | F23: =F10-F21 | G23: =G10-G21 | H23: =H10-H21
B25: ↑ 추정 라인을 채우면 소계·검증(23행)이 자동 계산됩니다. 검증=0 이면 성공! (R5)

Sheet CF
B1: 현금흐름표 (Cash Flow, 간접법)
B2: 단위: 억원 · 추정연도 산출
B3: 항목 | C3: 2022A | D3: 2023A | E3: 2024A | F3: 2025E | G3: 2026E | H3: 2027E
B5: [ 영업활동 ]
B6: 당기순이익
B7: (+) 감가상각비
B8: (-) 매출채권 증감
B9: (-) 재고자산 증감
B10: (+) 매입채무 증감
B11: 영업활동 현금흐름 | F11: =SUM(F6:F10) | G11: =SUM(G6:G10) | H11: =SUM(H6:H10)
B13: [ 투자활동 ]
B14: (-) Capex
B15: 투자활동 현금흐름 | F15: =F14 | G15: =G14 | H15: =H14
B17: [ 재무활동 ]
B18: 차입금 증감
B19: (-) 배당금
B20: 재무활동 현금흐름 | F20: =SUM(F18:F19) | G20: =SUM(G18:G19) | H20: =SUM(H18:H19)
B22: 순현금흐름 | F22: =F11+F15+F20 | G22: =G11+G15+G20 | H22: =H11+H15+H20
B23: 기초 현금
B24: 기말 현금 | F24: =F22+F23 | G24: =G22+G23 | H24: =H22+H23
B26: ↑ 영업/투자/재무 라인을 채우면 기말현금이 BS 현금과 연결됩니다. (R5)

Sheet Ratios
B1: 재무비율 대시보드
B2: IS·BS에서 자동 산출
B3: 항목 | C3: 2022A | D3: 2023A | E3: 2024A | F3: 2025E | G3: 2026E | H3: 2027E
B4: [ 수익성 ]
B5: 매출총이익률 | C5: =IFERROR(IS!C6/IS!C4,"-") | D5: =IFERROR(IS!D6/IS!D4,"-") | E5: =IFERROR(IS!E6/IS!E4,"-") | F5: =IFERROR(IS!F6/IS!F4,"-") | G5: =IFERROR(IS!G6/IS!G4,"-") | H5: =IFERROR(IS!H6/IS!H4,"-")
B6: 영업이익률 | C6: =IFERROR(IS!C8/IS!C4,"-") | D6: =IFERROR(IS!D8/IS!D4,"-") | E6: =IFERROR(IS!E8/IS!E4,"-") | F6: =IFERROR(IS!F8/IS!F4,"-") | G6: =IFERROR(IS!G8/IS!G4,"-") | H6: =IFERROR(IS!H8/IS!H4,"-")
B7: 순이익률 | C7: =IFERROR(IS!C12/IS!C4,"-") | D7: =IFERROR(IS!D12/IS!D4,"-") | E7: =IFERROR(IS!E12/IS!E4,"-") | F7: =IFERROR(IS!F12/IS!F4,"-") | G7: =IFERROR(IS!G12/IS!G4,"-") | H7: =IFERROR(IS!H12/IS!H4,"-")
B8: ROE | C8: =IFERROR(IS!C12/BS!C20,"-") | D8: =IFERROR(IS!D12/BS!D20,"-") | E8: =IFERROR(IS!E12/BS!E20,"-") | F8: =IFERROR(IS!F12/BS!F20,"-") | G8: =IFERROR(IS!G12/BS!G20,"-") | H8: =IFERROR(IS!H12/BS!H20,"-")
B9: ROA | C9: =IFERROR(IS!C12/BS!C10,"-") | D9: =IFERROR(IS!D12/BS!D10,"-") | E9: =IFERROR(IS!E12/BS!E10,"-") | F9: =IFERROR(IS!F12/BS!F10,"-") | G9: =IFERROR(IS!G12/BS!G10,"-") | H9: =IFERROR(IS!H12/BS!H10,"-")
B10: [ 성장성 ]
B11: 매출 YoY | C11: =IS!C14 | D11: =IS!D14 | E11: =IS!E14 | F11: =IS!F14 | G11: =IS!G14 | H11: =IS!H14
B12: 영업이익 YoY | C12: =IFERROR(IS!C8/IS!C8-1,"-") | D12: =IFERROR(IS!D8/IS!C8-1,"-") | E12: =IFERROR(IS!E8/IS!D8-1,"-") | F12: =IFERROR(IS!F8/IS!E8-1,"-") | G12: =IFERROR(IS!G8/IS!F8-1,"-") | H12: =IFERROR(IS!H8/IS!G8-1,"-")
B13: [ 안정성 ]
B14: 부채비율 | C14: =IFERROR(BS!C15/BS!C20,"-") | D14: =IFERROR(BS!D15/BS!D20,"-") | E14: =IFERROR(BS!E15/BS!E20,"-") | F14: =IFERROR(BS!F15/BS!F20,"-") | G14: =IFERROR(BS!G15/BS!G20,"-") | H14: =IFERROR(BS!H15/BS!H20,"-")
B15: 이자보상배율 | C15: =IFERROR(IS!C8/IS!C9,"-") | D15: =IFERROR(IS!D8/IS!D9,"-") | E15: =IFERROR(IS!E8/IS!E9,"-") | F15: =IFERROR(IS!F8/IS!F9,"-") | G15: =IFERROR(IS!G8/IS!G9,"-") | H15: =IFERROR(IS!H8/IS!H9,"-")
B16: [ 활동성 ]
B17: 매출채권 회전일 | C17: =IFERROR(BS!C7/IS!C4*365,"-") | D17: =IFERROR(BS!D7/IS!D4*365,"-") | E17: =IFERROR(BS!E7/IS!E4*365,"-") | F17: =IFERROR(BS!F7/IS!F4*365,"-") | G17: =IFERROR(BS!G7/IS!G4*365,"-") | H17: =IFERROR(BS!H7/IS!H4*365,"-")
B18: 재고 회전일 | C18: =IFERROR(BS!C8/IS!C5*365,"-") | D18: =IFERROR(BS!D8/IS!D5*365,"-") | E18: =IFERROR(BS!E8/IS!E5*365,"-") | F18: =IFERROR(BS!F8/IS!F5*365,"-") | G18: =IFERROR(BS!G8/IS!G5*365,"-") | H18: =IFERROR(BS!H8/IS!H5*365,"-")

Sheet DCF
B1: DCF 밸류에이션
B2: 단위: 억원 · 주당 원
B3: 항목 | C3: 2025E | D3: 2026E | E3: 2027E
B4: 영업이익 (EBIT)
B5: EBIT×(1-t)
B6: (+) 감가상각비
B7: (-) Capex
B8: (-) 순운전자본 증감
B9: FCFF | C9: =C5+C6+C7+C8 | D9: =D5+D6+D7+D8 | E9: =E5+E6+E7+E8
B10: 할인연차 n | C10: 1 | D10: 2 | E10: 3
B11: 할인계수 | C11: =1/(1+가정!$C$15)^C10 | D11: =1/(1+가정!$C$15)^D10 | E11: =1/(1+가정!$C$15)^E10
B12: PV(FCFF) | C12: =C9*C11 | D12: =D9*D11 | E12: =E9*E11
B14: PV(FCFF) 합계 | C14: =SUM(C12:E12)
B15: 영구가치 (TV) | C15: =E9*(1+가정!$C$16)/(가정!$C$15-가정!$C$16)
B16: PV(TV) | C16: =C15*E11
B17: 기업가치 (EV) | C17: =C14+C16
B18: (-) 순차입금 | C18: =BS!E14-BS!E6
B19: 자기자본가치 | C19: =C17-C18
B20: 주식수(백만주) | C20: =가정!$C$17
B21: 주당 내재가치(원) | C21: =C19*100000000/(C20*1000000)
B22: (참고) 현재주가(원) | C22: 4000
B23: 상승여력 | C23: =IFERROR(C21/C22-1,"-")
B25: ↑ FCFF 구성(EBIT~ΔNWC)만 채우면 EV·주당가치·민감도·투자의견이 자동 산출됩니다. (R6)
B26: 주당가치 민감도 — WACC × 영구성장률 g
C27: WACC＼g | D27: 0.01 | E27: 0.015 | F27: 0.02 | G27: 0.025 | H27: 0.03
C28: 0.08 | D28: =($C$9/(1+$C28)^1+$D$9/(1+$C28)^2+$E$9/(1+$C28)^3+($E$9*(1+D$27)/($C28-D$27))/(1+$C28)^3-$C$18)*100000000/($C$20*1000000) | E28: =($C$9/(1+$C28)^1+$D$9/(1+$C28)^2+$E$9/(1+$C28)^3+($E$9*(1+E$27)/($C28-E$27))/(1+$C28)^3-$C$18)*100000000/($C$20*1000000) | F28: =($C$9/(1+$C28)^1+$D$9/(1+$C28)^2+$E$9/(1+$C28)^3+($E$9*(1+F$27)/($C28-F$27))/(1+$C28)^3-$C$18)*100000000/($C$20*1000000) | G28: =($C$9/(1+$C28)^1+$D$9/(1+$C28)^2+$E$9/(1+$C28)^3+($E$9*(1+G$27)/($C28-G$27))/(1+$C28)^3-$C$18)*100000000/($C$20*1000000) | H28: =($C$9/(1+$C28)^1+$D$9/(1+$C28)^2+$E$9/(1+$C28)^3+($E$9*(1+H$27)/($C28-H$27))/(1+$C28)^3-$C$18)*100000000/($C$20*1000000)
C29: 0.085 | D29: =($C$9/(1+$C29)^1+$D$9/(1+$C29)^2+$E$9/(1+$C29)^3+($E$9*(1+D$27)/($C29-D$27))/(1+$C29)^3-$C$18)*100000000/($C$20*1000000) | E29: =($C$9/(1+$C29)^1+$D$9/(1+$C29)^2+$E$9/(1+$C29)^3+($E$9*(1+E$27)/($C29-E$27))/(1+$C29)^3-$C$18)*100000000/($C$20*1000000) | F29: =($C$9/(1+$C29)^1+$D$9/(1+$C29)^2+$E$9/(1+$C29)^3+($E$9*(1+F$27)/($C29-F$27))/(1+$C29)^3-$C$18)*100000000/($C$20*1000000) | G29: =($C$9/(1+$C29)^1+$D$9/(1+$C29)^2+$E$9/(1+$C29)^3+($E$9*(1+G$27)/($C29-G$27))/(1+$C29)^3-$C$18)*100000000/($C$20*1000000) | H29: =($C$9/(1+$C29)^1+$D$9/(1+$C29)^2+$E$9/(1+$C29)^3+($E$9*(1+H$27)/($C29-H$27))/(1+$C29)^3-$C$18)*100000000/($C$20*1000000)
C30: 0.09 | D30: =($C$9/(1+$C30)^1+$D$9/(1+$C30)^2+$E$9/(1+$C30)^3+($E$9*(1+D$27)/($C30-D$27))/(1+$C30)^3-$C$18)*100000000/($C$20*1000000) | E30: =($C$9/(1+$C30)^1+$D$9/(1+$C30)^2+$E$9/(1+$C30)^3+($E$9*(1+E$27)/($C30-E$27))/(1+$C30)^3-$C$18)*100000000/($C$20*1000000) | F30: =($C$9/(1+$C30)^1+$D$9/(1+$C30)^2+$E$9/(1+$C30)^3+($E$9*(1+F$27)/($C30-F$27))/(1+$C30)^3-$C$18)*100000000/($C$20*1000000) | G30: =($C$9/(1+$C30)^1+$D$9/(1+$C30)^2+$E$9/(1+$C30)^3+($E$9*(1+G$27)/($C30-G$27))/(1+$C30)^3-$C$18)*100000000/($C$20*1000000) | H30: =($C$9/(1+$C30)^1+$D$9/(1+$C30)^2+$E$9/(1+$C30)^3+($E$9*(1+H$27)/($C30-H$27))/(1+$C30)^3-$C$18)*100000000/($C$20*1000000)
C31: 0.095 | D31: =($C$9/(1+$C31)^1+$D$9/(1+$C31)^2+$E$9/(1+$C31)^3+($E$9*(1+D$27)/($C31-D$27))/(1+$C31)^3-$C$18)*100000000/($C$20*1000000) | E31: =($C$9/(1+$C31)^1+$D$9/(1+$C31)^2+$E$9/(1+$C31)^3+($E$9*(1+E$27)/($C31-E$27))/(1+$C31)^3-$C$18)*100000000/($C$20*1000000) | F31: =($C$9/(1+$C31)^1+$D$9/(1+$C31)^2+$E$9/(1+$C31)^3+($E$9*(1+F$27)/($C31-F$27))/(1+$C31)^3-$C$18)*100000000/($C$20*1000000) | G31: =($C$9/(1+$C31)^1+$D$9/(1+$C31)^2+$E$9/(1+$C31)^3+($E$9*(1+G$27)/($C31-G$27))/(1+$C31)^3-$C$18)*100000000/($C$20*1000000) | H31: =($C$9/(1+$C31)^1+$D$9/(1+$C31)^2+$E$9/(1+$C31)^3+($E$9*(1+H$27)/($C31-H$27))/(1+$C31)^3-$C$18)*100000000/($C$20*1000000)
C32: 0.1 | D32: =($C$9/(1+$C32)^1+$D$9/(1+$C32)^2+$E$9/(1+$C32)^3+($E$9*(1+D$27)/($C32-D$27))/(1+$C32)^3-$C$18)*100000000/($C$20*1000000) | E32: =($C$9/(1+$C32)^1+$D$9/(1+$C32)^2+$E$9/(1+$C32)^3+($E$9*(1+E$27)/($C32-E$27))/(1+$C32)^3-$C$18)*100000000/($C$20*1000000) | F32: =($C$9/(1+$C32)^1+$D$9/(1+$C32)^2+$E$9/(1+$C32)^3+($E$9*(1+F$27)/($C32-F$27))/(1+$C32)^3-$C$18)*100000000/($C$20*1000000) | G32: =($C$9/(1+$C32)^1+$D$9/(1+$C32)^2+$E$9/(1+$C32)^3+($E$9*(1+G$27)/($C32-G$27))/(1+$C32)^3-$C$18)*100000000/($C$20*1000000) | H32: =($C$9/(1+$C32)^1+$D$9/(1+$C32)^2+$E$9/(1+$C32)^3+($E$9*(1+H$27)/($C32-H$27))/(1+$C32)^3-$C$18)*100000000/($C$20*1000000)

Sheet Output
B1: 투자 요약 (Investment Summary)
B2: 활성 시나리오 기준 · 가정 시트에서 시나리오 전환
B4: 시나리오 | C4: =CHOOSE(가정!$E$1,"Base","Bull","Bear")
B5: 기업가치 (EV, 억) | C5: =DCF!C17
B6: 자기자본가치 (억) | C6: =DCF!C19
B7: 목표주가 | C7: =DCF!C21
B8: 현재주가 | C8: =DCF!C22
B9: 상승여력 | C9: =DCF!C23
B10: 투자의견 | C10: =IFERROR(IF(C9>0.15,"매수 (Buy)",IF(C9<-0.1,"매도 (Sell)","중립 (Hold)")),"-")
B12: 매출·영업이익 추이 (억)
