Workbook

Sheet 가정
B1: 가정 (Assumptions)
B2: 단위: 억원 · 주식수 백만주 · 파란 셀만 바꾸면 모델 전체가 갱신됩니다
B3: 항목 | C3: 값 | D3: 비고
B4: 매출성장률 (추정연도) | C4: 0.07 | D4: YoY, 추정연도 공통 적용
B5: 매출원가율 (COGS/매출) | C5: 0.62
B6: 판매관리비율 (SG&A/매출) | C6: 0.2
B7: 법인세율 | C7: 0.22
B8: Capex / 매출 | C8: 0.05
B9: 감가상각률 (기초 유형자산 대비) | C9: 0.1
B10: 매출채권 회수기간 DSO (일) | C10: 45
B11: 재고자산 보유기간 DIO (일) | C11: 60
B12: 매입채무 지급기간 DPO (일) | C12: 40
B13: 배당성향 | C13: 0.2
B14: 차입금 이자율 | C14: 0.045 | D14: 기초 차입금 기준
B15: WACC (할인율) | C15: 0.09
B16: 영구성장률 g | C16: 0.02 | D16: < WACC
B17: 주식수 (백만주) | C17: 50

Sheet IS
B1: 손익계산서 (Income Statement)
B2: 단위: 억원
B3: 항목 | C3: 2022A | D3: 2023A | E3: 2024A | F3: 2025E | G3: 2026E | H3: 2027E
B4: 매출액 | C4: 1000 | D4: 1120 | E4: 1230 | F4: =E4*(1+가정!$C$4) | G4: =F4*(1+가정!$C$4) | H4: =G4*(1+가정!$C$4)
B5: (-) 매출원가 | C5: 620 | D5: 694 | E5: 763 | F5: =F4*가정!$C$5 | G5: =G4*가정!$C$5 | H5: =H4*가정!$C$5
B6: 매출총이익 | C6: =C4-C5 | D6: =D4-D5 | E6: =E4-E5 | F6: =F4-F5 | G6: =G4-G5 | H6: =H4-H5
B7: (-) 판매관리비 | C7: 200 | D7: 224 | E7: 246 | F7: =F4*가정!$C$6 | G7: =G4*가정!$C$6 | H7: =H4*가정!$C$6
B8: 영업이익 (EBIT) | C8: =C6-C7 | D8: =D6-D7 | E8: =E6-E7 | F8: =F6-F7 | G8: =G6-G7 | H8: =H6-H7
B9: (-) 이자비용 | C9: 18 | D9: 19 | E9: 20 | F9: =가정!$C$14*BS!E14 | G9: =가정!$C$14*BS!F14 | H9: =가정!$C$14*BS!G14
B10: 세전이익 | C10: =C8-C9 | D10: =D8-D9 | E10: =E8-E9 | F10: =F8-F9 | G10: =G8-G9 | H10: =H8-H9
B11: (-) 법인세 | C11: 36 | D11: 40 | E11: 44 | F11: =F10*가정!$C$7 | G11: =G10*가정!$C$7 | H11: =H10*가정!$C$7
B12: 당기순이익 | C12: =C10-C11 | D12: =D10-D11 | E12: =E10-E11 | F12: =F10-F11 | G12: =G10-G11 | H12: =H10-H11
B15: 영업이익률 | C15: =C8/C4 | D15: =D8/D4 | E15: =E8/E4 | F15: =F8/F4 | G15: =G8/G4 | H15: =H8/H4

Sheet BS
B1: 재무상태표 (Balance Sheet)
B2: 단위: 억원
B3: 항목 | C3: 2022A | D3: 2023A | E3: 2024A | F3: 2025E | G3: 2026E | H3: 2027E
B5: [ 자산 ]
B6: 현금및현금성자산 | C6: 344 | D6: 419 | E6: 508 | F6: =CF!F24 | G6: =CF!G24 | H6: =CF!H24
B7: 매출채권 | C7: 123 | D7: 138 | E7: 152 | F7: =IS!F4*가정!$C$10/365 | G7: =IS!G4*가정!$C$10/365 | H7: =IS!H4*가정!$C$10/365
B8: 재고자산 | C8: 102 | D8: 114 | E8: 125 | F8: =IS!F5*가정!$C$11/365 | G8: =IS!G5*가정!$C$11/365 | H8: =IS!H5*가정!$C$11/365
B9: 유형자산(순) | C9: 500 | D9: 540 | E9: 580 | F9: =E9+가정!$C$8*IS!F4-가정!$C$9*E9 | G9: =F9+가정!$C$8*IS!G4-가정!$C$9*F9 | H9: =G9+가정!$C$8*IS!H4-가정!$C$9*G9
B10: 자산총계 | C10: =SUM(C6:C9) | D10: =SUM(D6:D9) | E10: =SUM(E6:E9) | F10: =SUM(F6:F9) | G10: =SUM(G6:G9) | H10: =SUM(H6:H9)
B12: [ 부채 ]
B13: 매입채무 | C13: 68 | D13: 76 | E13: 84 | F13: =IS!F5*가정!$C$12/365 | G13: =IS!G5*가정!$C$12/365 | H13: =IS!H5*가정!$C$12/365
B14: 차입금 | C14: 400 | D14: 420 | E14: 440 | F14: =E14 | G14: =F14 | H14: =G14
B15: 부채총계 | C15: =SUM(C13:C14) | D15: =SUM(D13:D14) | E15: =SUM(E13:E14) | F15: =SUM(F13:F14) | G15: =SUM(G13:G14) | H15: =SUM(H13:H14)
B17: [ 자본 ]
B18: 자본금 | C18: 300 | D18: 300 | E18: 300 | F18: =E18 | G18: =F18 | H18: =G18
B19: 이익잉여금 | C19: 301 | D19: 415 | E19: 541 | F19: =E19+IS!F12-가정!$C$13*IS!F12 | G19: =F19+IS!G12-가정!$C$13*IS!G12 | H19: =G19+IS!H12-가정!$C$13*IS!H12
B20: 자본총계 | C20: =SUM(C18:C19) | D20: =SUM(D18:D19) | E20: =SUM(E18:E19) | F20: =SUM(F18:F19) | G20: =SUM(G18:G19) | H20: =SUM(H18:H19)
B21: 부채와자본총계 | C21: =C15+C20 | D21: =D15+D20 | E21: =E15+E20 | F21: =F15+F20 | G21: =G15+G20 | H21: =H15+H20
B23: 검증 (자산-부채-자본) | C23: =C10-C21 | D23: =D10-D21 | E23: =E10-E21 | F23: =F10-F21 | G23: =G10-G21 | H23: =H10-H21

Sheet CF
B1: 현금흐름표 (Cash Flow, 간접법)
B2: 단위: 억원 · 추정연도만 산출
B3: 항목 | C3: 2022A | D3: 2023A | E3: 2024A | F3: 2025E | G3: 2026E | H3: 2027E
B5: [ 영업활동 ]
B6: 당기순이익 | F6: =IS!F12 | G6: =IS!G12 | H6: =IS!H12
B7: (+) 감가상각비 | F7: =가정!$C$9*BS!E9 | G7: =가정!$C$9*BS!F9 | H7: =가정!$C$9*BS!G9
B8: (-) 매출채권 증감 | F8: =-(BS!F7-BS!E7) | G8: =-(BS!G7-BS!F7) | H8: =-(BS!H7-BS!G7)
B9: (-) 재고자산 증감 | F9: =-(BS!F8-BS!E8) | G9: =-(BS!G8-BS!F8) | H9: =-(BS!H8-BS!G8)
B10: (+) 매입채무 증감 | F10: =BS!F13-BS!E13 | G10: =BS!G13-BS!F13 | H10: =BS!H13-BS!G13
B11: 영업활동 현금흐름 | F11: =SUM(F6:F10) | G11: =SUM(G6:G10) | H11: =SUM(H6:H10)
B13: [ 투자활동 ]
B14: (-) Capex | F14: =-가정!$C$8*IS!F4 | G14: =-가정!$C$8*IS!G4 | H14: =-가정!$C$8*IS!H4
B15: 투자활동 현금흐름 | F15: =F14 | G15: =G14 | H15: =H14
B17: [ 재무활동 ]
B18: 차입금 증감 | F18: =BS!F14-BS!E14 | G18: =BS!G14-BS!F14 | H18: =BS!H14-BS!G14
B19: (-) 배당금 | F19: =-가정!$C$13*IS!F12 | G19: =-가정!$C$13*IS!G12 | H19: =-가정!$C$13*IS!H12
B20: 재무활동 현금흐름 | F20: =SUM(F18:F19) | G20: =SUM(G18:G19) | H20: =SUM(H18:H19)
B22: 순현금흐름 | F22: =F11+F15+F20 | G22: =G11+G15+G20 | H22: =H11+H15+H20
B23: 기초 현금 | F23: =BS!E6 | G23: =BS!F6 | H23: =BS!G6
B24: 기말 현금 | F24: =F22+F23 | G24: =G22+G23 | H24: =H22+H23

Sheet DCF
B1: DCF 밸류에이션
B2: 단위: 억원 · 주당가치 원
B3: 항목 | C3: 2025E | D3: 2026E | E3: 2027E
B4: 영업이익 (EBIT) | C4: =IS!F8 | D4: =IS!G8 | E4: =IS!H8
B5: EBIT×(1-t) | C5: =C4*(1-가정!$C$7) | D5: =D4*(1-가정!$C$7) | E5: =E4*(1-가정!$C$7)
B6: (+) 감가상각비 | C6: =가정!$C$9*BS!E9 | D6: =가정!$C$9*BS!F9 | E6: =가정!$C$9*BS!G9
B7: (-) Capex | C7: =-가정!$C$8*IS!F4 | D7: =-가정!$C$8*IS!G4 | E7: =-가정!$C$8*IS!H4
B8: (-) 순운전자본 증감 | C8: =-((BS!F7+BS!F8-BS!F13)-(BS!E7+BS!E8-BS!E13)) | D8: =-((BS!G7+BS!G8-BS!G13)-(BS!F7+BS!F8-BS!F13)) | E8: =-((BS!H7+BS!H8-BS!H13)-(BS!G7+BS!G8-BS!G13))
B9: FCFF | C9: =C5+C6+C7+C8 | D9: =D5+D6+D7+D8 | E9: =E5+E6+E7+E8
B10: 할인연차 n | C10: 1 | D10: 2 | E10: 3
B11: 할인계수 | C11: =1/(1+가정!$C$15)^C10 | D11: =1/(1+가정!$C$15)^D10 | E11: =1/(1+가정!$C$15)^E10
B12: PV(FCFF) | C12: =C9*C11 | D12: =D9*D11 | E12: =E9*E11
B14: PV(FCFF) 합계 | C14: =SUM(C12:E12)
B15: 영구가치 (TV) | C15: =E9*(1+가정!$C$16)/(가정!$C$15-가정!$C$16)
B16: PV(TV) | C16: =C15*E11
B17: 기업가치 (EV) | C17: =C14+C16
B18: (-) 순차입금 | C18: =BS!E14-BS!E6
B19: 자기자본가치 | C19: =C17-C18
B20: 주식수 (백만주) | C20: =가정!$C$17
B21: 주당 내재가치 (원) | C21: =C19*100000000/(C20*1000000)
B22: (참고) 현재주가 (원) | C22: 4000
B23: 상승여력 | C23: =C21/C22-1
B26: 주당가치 민감도 (WACC × 영구성장률 g)
C27: WACC \ g | D27: 0.01 | E27: 0.015 | F27: 0.02 | G27: 0.025 | H27: 0.03
C28: 0.08 | D28: =($C$9/(1+$C28)^1+$D$9/(1+$C28)^2+$E$9/(1+$C28)^3+($E$9*(1+D$27)/($C28-D$27))/(1+$C28)^3-$C$18)*100000000/($C$20*1000000) | E28: =($C$9/(1+$C28)^1+$D$9/(1+$C28)^2+$E$9/(1+$C28)^3+($E$9*(1+E$27)/($C28-E$27))/(1+$C28)^3-$C$18)*100000000/($C$20*1000000) | F28: =($C$9/(1+$C28)^1+$D$9/(1+$C28)^2+$E$9/(1+$C28)^3+($E$9*(1+F$27)/($C28-F$27))/(1+$C28)^3-$C$18)*100000000/($C$20*1000000) | G28: =($C$9/(1+$C28)^1+$D$9/(1+$C28)^2+$E$9/(1+$C28)^3+($E$9*(1+G$27)/($C28-G$27))/(1+$C28)^3-$C$18)*100000000/($C$20*1000000) | H28: =($C$9/(1+$C28)^1+$D$9/(1+$C28)^2+$E$9/(1+$C28)^3+($E$9*(1+H$27)/($C28-H$27))/(1+$C28)^3-$C$18)*100000000/($C$20*1000000)
C29: 0.085 | D29: =($C$9/(1+$C29)^1+$D$9/(1+$C29)^2+$E$9/(1+$C29)^3+($E$9*(1+D$27)/($C29-D$27))/(1+$C29)^3-$C$18)*100000000/($C$20*1000000) | E29: =($C$9/(1+$C29)^1+$D$9/(1+$C29)^2+$E$9/(1+$C29)^3+($E$9*(1+E$27)/($C29-E$27))/(1+$C29)^3-$C$18)*100000000/($C$20*1000000) | F29: =($C$9/(1+$C29)^1+$D$9/(1+$C29)^2+$E$9/(1+$C29)^3+($E$9*(1+F$27)/($C29-F$27))/(1+$C29)^3-$C$18)*100000000/($C$20*1000000) | G29: =($C$9/(1+$C29)^1+$D$9/(1+$C29)^2+$E$9/(1+$C29)^3+($E$9*(1+G$27)/($C29-G$27))/(1+$C29)^3-$C$18)*100000000/($C$20*1000000) | H29: =($C$9/(1+$C29)^1+$D$9/(1+$C29)^2+$E$9/(1+$C29)^3+($E$9*(1+H$27)/($C29-H$27))/(1+$C29)^3-$C$18)*100000000/($C$20*1000000)
C30: 0.09 | D30: =($C$9/(1+$C30)^1+$D$9/(1+$C30)^2+$E$9/(1+$C30)^3+($E$9*(1+D$27)/($C30-D$27))/(1+$C30)^3-$C$18)*100000000/($C$20*1000000) | E30: =($C$9/(1+$C30)^1+$D$9/(1+$C30)^2+$E$9/(1+$C30)^3+($E$9*(1+E$27)/($C30-E$27))/(1+$C30)^3-$C$18)*100000000/($C$20*1000000) | F30: =($C$9/(1+$C30)^1+$D$9/(1+$C30)^2+$E$9/(1+$C30)^3+($E$9*(1+F$27)/($C30-F$27))/(1+$C30)^3-$C$18)*100000000/($C$20*1000000) | G30: =($C$9/(1+$C30)^1+$D$9/(1+$C30)^2+$E$9/(1+$C30)^3+($E$9*(1+G$27)/($C30-G$27))/(1+$C30)^3-$C$18)*100000000/($C$20*1000000) | H30: =($C$9/(1+$C30)^1+$D$9/(1+$C30)^2+$E$9/(1+$C30)^3+($E$9*(1+H$27)/($C30-H$27))/(1+$C30)^3-$C$18)*100000000/($C$20*1000000)
C31: 0.095 | D31: =($C$9/(1+$C31)^1+$D$9/(1+$C31)^2+$E$9/(1+$C31)^3+($E$9*(1+D$27)/($C31-D$27))/(1+$C31)^3-$C$18)*100000000/($C$20*1000000) | E31: =($C$9/(1+$C31)^1+$D$9/(1+$C31)^2+$E$9/(1+$C31)^3+($E$9*(1+E$27)/($C31-E$27))/(1+$C31)^3-$C$18)*100000000/($C$20*1000000) | F31: =($C$9/(1+$C31)^1+$D$9/(1+$C31)^2+$E$9/(1+$C31)^3+($E$9*(1+F$27)/($C31-F$27))/(1+$C31)^3-$C$18)*100000000/($C$20*1000000) | G31: =($C$9/(1+$C31)^1+$D$9/(1+$C31)^2+$E$9/(1+$C31)^3+($E$9*(1+G$27)/($C31-G$27))/(1+$C31)^3-$C$18)*100000000/($C$20*1000000) | H31: =($C$9/(1+$C31)^1+$D$9/(1+$C31)^2+$E$9/(1+$C31)^3+($E$9*(1+H$27)/($C31-H$27))/(1+$C31)^3-$C$18)*100000000/($C$20*1000000)
C32: 0.1 | D32: =($C$9/(1+$C32)^1+$D$9/(1+$C32)^2+$E$9/(1+$C32)^3+($E$9*(1+D$27)/($C32-D$27))/(1+$C32)^3-$C$18)*100000000/($C$20*1000000) | E32: =($C$9/(1+$C32)^1+$D$9/(1+$C32)^2+$E$9/(1+$C32)^3+($E$9*(1+E$27)/($C32-E$27))/(1+$C32)^3-$C$18)*100000000/($C$20*1000000) | F32: =($C$9/(1+$C32)^1+$D$9/(1+$C32)^2+$E$9/(1+$C32)^3+($E$9*(1+F$27)/($C32-F$27))/(1+$C32)^3-$C$18)*100000000/($C$20*1000000) | G32: =($C$9/(1+$C32)^1+$D$9/(1+$C32)^2+$E$9/(1+$C32)^3+($E$9*(1+G$27)/($C32-G$27))/(1+$C32)^3-$C$18)*100000000/($C$20*1000000) | H32: =($C$9/(1+$C32)^1+$D$9/(1+$C32)^2+$E$9/(1+$C32)^3+($E$9*(1+H$27)/($C32-H$27))/(1+$C32)^3-$C$18)*100000000/($C$20*1000000)
